Workbook

Sheet Hoja1
A1: Temario | B1: Tema | C1: Descripcion_Tema | D1: Test | E1: Descripcion_test | F1: Pregunta | G1: Enunciado | H1: a | I1: b | J1: c | K1: d | L1: solucion
A2: Jurídico | B2: 1 | C2: Constitución | D2: 1 | E2: Test Ayuntamiento 1 | F2: 1 | G2: A tenor del contenido del articulo 1.1. de la Constitucion española de 1978, ¿en que tipo de Estado se constituyo el Estado español? | H2: Social, liberal y de derecho. | I2: Democratico, de derecho y social | J2: Social, democratico y capitalista | L2: b
A3: Jurídico | B3: 1 | C3: Constitución | D3: 1 | E3: Test Ayuntamiento 1 | F3: 2 | G3: El Estatuto de Autonomia es: | H3: Una norma estatal, al ser parte de su ordenamiento juridico. | I3: Norma institucional basica de cada CCAA | J3: Ley Organica cualificada en su elaboracion, tramitacion y reforma | L3: b
A4: Jurídico | B4: 1 | C4: Constitución | D4: 2 | E4: Test Constitución 16 2023 | F4: 1 | G4: ¿En qué parte de la Constitución se señalan los valores del ordenamiento jurídico? | H4: En el Preámbulo | I4: En el Título Preliminar | J4: En El Título I | K4: Ninguna respuesta es correcta | L4: b
A5: Jurídico | B5: 1 | C5: Constitución | D5: 2 | E5: Test Constitución 16 2023 | F5: 2 | G5: Los valores superiores del ordenamiento jurídico son: | H5: Libertad, justicia, seguridad y pluralismo político | I5: Seguridad, justicia, igualdad y pluralismo político | J5: Libertad, justicia, pluralismo político e igualdad | K5: Ninguna respuesta es correcta | L5: c
A6: Jurídico | B6: 1 | C6: Constitución | D6: 2 | E6: Test Constitución 16 2023 | F6: 3 | G6: Son el fundamento del orden político y de la paz social: | H6: El libre desarrollo de la personalidad | I6: Los derechos inviolables que le son inherentes | J6: El respeto a la Ley y a los derechos de los demás | K6: Todas las respuestas son correctas | L6: d
A7: Jurídico | B7: 1 | C7: Constitución | D7: 2 | E7: Test Constitución 16 2023 | F7: 4 | G7: Según la Constitución, debe garantizarse siempre la audiencia de los ciudadanos en el: | H7: Procedimiento de elaboración de las disposiciones administrativas que le afecten. | I7: Procedimiento a través del cual se produzcan los actos administrativos. | J7: Total actuar de la administración. | K7: Procedimiento de elaboración de las disposiciones administrativas que le afecten y en el procedimiento a través del cual se produzcan los actos administrativos. | L7: a
A8: Jurídico | B8: 1 | C8: Constitución | D8: 2 | E8: Test Constitución 16 2023 | F8: 5 | G8: Los órganos de la Administración del Estado, son creados, regidos y coordinados: | H8: De acuerdo con los principios marcados por el Ministerio para las Administraciones Públicas. | I8: De acuerdo con los exigencias del Gobierno. | J8: De acuerdo con la Ley. | K8: De acuerdo con las exigencias de los ciudadanos. | L8: c
A9: Jurídico | B9: 1 | C9: Constitución | D9: 2 | E9: Test Constitución 16 2023 | F9: 6 | G9: El Consejo de Estado debe ser regulado: | H9: Mediante ley ordinaria. | I9: Puede serio mediante ley de bases. | J9: Puede ser objeto su regulación de delegación legislativa. | K9: Mediante ley orgánica. | L9: d
A10: Jurídico | B10: 1 | C10: Constitución | D10: 2 | E10: Test Constitución 16 2023 | F10: 7 | G10: ¿Quién representa al Gobierno estatal en una Comunidad Autónoma? | H10: El Delegado del Gobierno | I10: El Presidente de la Comunidad Autónoma | J10: El Consejo de Gobierno | K10: El Subdelegado del Gobierno | L10: a
A11: Jurídico | B11: 1 | C11: Constitución | D11: 2 | E11: Test Constitución 16 2023 | F11: 8 | G11: No podrán acceder al autogobierno: | H11: Las provincias con entidad regional histórica. | I11: Las provincias limítrofes con características económicas comunes. | J11: Los territorios insulares. | K11: Las provincias limítrofes con características sociales comunes. | L11: d
A12: Jurídico | B12: 1 | C12: Constitución | D12: 2 | E12: Test Constitución 16 2023 | F12: 9 | G12: El poder ejecutivo de una Comunidad Autónoma se ejerce por el: | H12: Consejo de Gobierno | I12: Consejo colegiado | J12: Consejo | K12: Consejo ejecutivo. | L12: a
A13: Jurídico | B13: 1 | C13: Constitución | D13: 2 | E13: Test Constitución 16 2023 | F13: 10 | G13: ¿A qué materia está dedicado el Título IV? | H13: A las Cortes Generales. | I13: Al Gobierno. | J13: Al Gobierno y a las Cortes Generales. | K13: Al Gobierno y a la Administración. | L13: d
A14: Jurídico | B14: 1 | C14: Constitución | D14: 2 | E14: Test Constitución 16 2023 | F14: 11 | G14: ¿En qué se fundamenta la Constitución, según el art. 2 de la misma? | H14: En el pueblo español que la refrendó. | I14: En la indisoluble unidad de la nación española. | J14: En el poder soberano de las Cortes Generales. | K14: En el estado democrático. | L14: b
A15: Jurídico | B15: 1 | C15: Constitución | D15: 2 | E15: Test Constitución 16 2023 | F15: 12 | G15: ¿Qué artículo del Título I recoge el principio de igualdad jurídica de los españoles ante la ley? | H15: El artículo 12. | I15: El artículo 11. | J15: El artículo 14. | K15: El artículo 16 | L15: c
... A79: Jurídico | B79: 1 | C79: Constitución | D79: 4 | E79: TEST CUCALON 2 | F79: 29 | G79: Se reconoce autonomía en la Constitución española a: | H79: A las comunidades autónomas y a las regiones | I79: A las regiones y a las nacionalidades | J79: A las regiones | K79: A las nacionalidades y comunidades autónomas | L79: b
A80: Jurídico | B80: 2 | C80: Ley Org. 5/2007 Estatuto de Autonomia | D80: 5 | E80: Test competencias 1 | F80: 5 | G80: En el ámbito de las competencias ejecutivas y en orden a la aplicación de la legislación estatal, la Comunidad Autónoma de Aragón podrá dictar reglamentos para la regulación de su propia competencia funcional y la organización de los servicios necesarios para ello, y en general podrá ejercer todas aquellas funciones y actividades que el ordenamiento jurídico atribuye a la Administración Pública. Corresponde a la Comunidad Autónoma la competencia ejecutiva en las siguientes materias: | H80: Gestión de la asistencia sanitaria de la Seguridad Social. Productos farmacéuticos. | I80: Museos, archivos, bibliotecas y otras colecciones de naturaleza análoga de titularidad estatal cuya gestión no se reserve la Administración General del Estado. | J80: A y B son correctas | L80: c
A81: Jurídico | B81: 2 | C81: Ley Org. 5/2007 Estatuto de Autonomia | D81: 5 | E81: Test competencias 1 | F81: 6 | G81: La materia referida a “Denominaciones de origen y otras menciones de calidad”, es una competencia de la Comunidad Autónoma de Aragón: | H81: Compartida. | I81: Exclusiva. | J81: Ejecutiva. | L81: b
A82: Jurídico | B82: 2 | C82: Ley Org. 5/2007 Estatuto de Autonomia | D82: 5 | E82: Test competencias 1 | F82: 7 | G82: La materia referida a “Ordenación del territorio, conforme a los principios de equilibrio territorial, demográfico, socioeconómico y ambiental”, es una competencia de la Comunidad Autónoma de Aragón: | H82: Compartida. | I82: Exclusiva. | J82: Ejecutiva. | L82: b
A83: Jurídico | B83: 2 | C83: Ley Org. 5/2007 Estatuto de Autonomia | D83: 5 | E83: Test competencias 1 | F83: 8 | G83: La materia referida a “Régimen jurídico, procedimiento, contratación y responsabilidad de la Administración Pública de la Comunidad Autónoma ”, es una competencia de la Comunidad Autónoma de Aragón: | H83: Compartida. | I83: Exclusiva. | J83: Ejecutiva. | L83: a
A84: Jurídico | B84: 2 | C84: Ley Org. 5/2007 Estatuto de Autonomia | D84: 5 | E84: Test competencias 1 | F84: 9 | G84: La materia referida a “Aeropuertos, helipuertos y otras infraestructuras de transporte aéreo, con calificación de interés general, cuya gestión directa no se reserve la Administración General del Estado”, es una competencia de la Comunidad Autónoma de Aragón: | H84: Compartida. | I84: Exclusiva. | J84: Ejecutiva. | L84: c
A85: Jurídico | B85: 2 | C85: Ley Org. 5/2007 Estatuto de Autonomia | D85: 5 | E85: Test competencias 1 | F85: 10 | G85: En el ámbito de las competencias exclusivas, la Comunidad Autónoma de Aragón ejercerá: | H85: El desarrollo legislativo, el reglamentario, la función ejecutiva y el establecimiento de políticas propias. | I85: La potestad legislativa, la potestad reglamentaria, la función ejecutiva y el establecimiento de políticas propias. | J85: Ninguna es correcta. | L85: b
A86: Jurídico | B86: 2 | C86: Ley Org. 5/2007 Estatuto de Autonomia | D86: 5 | E86: Test competencias 1 | F86: 11 | G86: La materia referida a “Políticas de igualdad social, que comprenden el establecimiento de medidas de discriminación positiva, prevención y protección social ante todo tipo de violencia, y, especialmente, la de género”, es una competencia de la Comunidad Autónoma de Aragón: | H86: Compartida. | I86: Exclusiva. | J86: Ejecutiva. | L86: b
A87: Jurídico | B87: 2 | C87: Ley Org. 5/2007 Estatuto de Autonomia | D87: 5 | E87: Test competencias 1 | F87: 12 | G87: La materia referida a “ Ordenación del crédito, banca, seguros, mutualidades de previsión social, entidades gestoras de planes y fondos de pensiones y otras mutualidades no integradas en el sistema de Seguridad Social ”, es una competencia de la Comunidad Autónoma de Aragón: | H87: Compartida. | I87: Exclusiva. | J87: Ejecutiva. | L87: a
A88: Jurídico | B88: 2 | C88: Ley Org. 5/2007 Estatuto de Autonomia | D88: 5 | E88: Test competencias 1 | F88: 13 | G88: La materia referida a “ Mercados de valores y centros de contratación situados en el territorio de Aragón, que, en todo caso, incluye su regulación, establecimiento y solvencia, de acuerdo con la legislación mercantil ”, es una competencia de la Comunidad Autónoma de Aragón: | H88: Compartida. | I88: Exclusiva. | J88: Ejecutiva. | L88: a
A89: Jurídico | B89: 2 | C89: Ley Org. 5/2007 Estatuto de Autonomia | D89: 5 | E89: Test competencias 1 | F89: 14 | G89: La regulación de la protección y defensa de los consumidores y usuarios; el fomento de las asociaciones; la formación y educación para el consumo responsable, es competencia: | H89: Exclusiva de la CCAA de Aragón. | I89: Exclusiva del Estado. | J89: Compartida. | L89: a
A90: Jurídico | B90: 2 | C90: Ley Org. 5/2007 Estatuto de Autonomia | D90: 5 | E90: Test competencias 1 | F90: 15 | G90: La materia referida a “Colaboración con el Estado en la gestión del catastro”, es una competencia de la Comunidad Autónoma de Aragón: | H90: Compartida. | I90: Exclusiva. | J90: Ejecutiva | L90: c
A91: Jurídico | B91: 2 | C91: Ley Org. 5/2007 Estatuto de Autonomia | D91: 5 | E91: Test competencias 1 | F91: 16 | G91: Cuando la Comunidad Autónoma de Aragón ejerce el desarrollo legislativo y la ejecución de la legislación básica que establezca el Estado, nos estamos refiriendo a competencias: | H91: Compartidas. | I91: Ejecutivas. | J91: Exclusivas. | L91: a
... A99: Jurídico | B99: 2 | C99: Ley Org. 5/2007 Estatuto de Autonomia | D99: 6 | E99: Test competencias 2 | F99: 4 | G99: La materia referida a “Colegios profesionales y ejercicio de profesiones tituladas”, es una competencia de la Comunidad Autónoma de Aragón: | H99: Exclusiva | I99: Compartida. | J99: Ejecutiva. | L99: a
A100: Jurídico | B100: 2 | C100: Ley Org. 5/2007 Estatuto de Autonomia | D100: 6 | E100: Test competencias 2 | F100: 5 | G100: El vigente Estatuto de Autonomía de Aragón aprobado por Ley orgánica 5/2007 de 20 de Abril, nos habla de tres tipos de competencias en su artículo 70: | H100: Competencias exclusivas, competencias compartidas y competencias generales. | I100: Competencias exclusivas. Competencias compartidas y competencias ejecutivas. | J100: Competencias exclusivas, competencias compartidas y competencias generales y competencias ejecutivas. | K100: Competencias exclusivas, competencias ejecutivas y competencias generales. | L100: b
A101: Jurídico | B101: 2 | C101: Ley Org. 5/2007 Estatuto de Autonomia | D101: 6 | E101: Test competencias 2 | F101: 6 | G101: Según dispone el artículo 74 del Estatuto de Autonomía de Aragón, la competencia en medios de comunicación social y servicios de contenido audiovisual es: | H101: Una competencia exclusiva. | I101: Una competencia compartida. | J101: Una competencia concurrente. | K101: Una competencia concurrente y además ejecutiva. | L101: b
A102: Jurídico | B102: 2 | C102: Ley Org. 5/2007 Estatuto de Autonomia | D102: 6 | E102: Test competencias 2 | F102: 7 | G102: Señala la falsa. Es competencia exclusiva de la Comunidad Autónoma de Aragón: | H102: El control metrológico y el contraste de metales. | I102: La organización territorial propia de la Comunidad Autónoma. | J102: Vivienda, que, en todo caso, incluye la planificación, la ordenación, la gestión, el fomento, la inspección y el control de la vivienda de acuerdo con las necesidades sociales de equilibrio territorial y de sostenibilidad. | L102: a
A103: Jurídico | B103: 2 | C103: Ley Org. 5/2007 Estatuto de Autonomia | D103: 6 | E103: Test competencias 2 | F103: 8 | G103: Sanidad y salud pública, en especial, la organización, el funcionamiento, la evaluación, la inspección y el control de centros, servicios y establecimientos sanitarios, es para la Comunidad Autónoma de Aragón, conforme al Estatuto de Autonomía de Aragón una competencia: | H103: Exclusiva. | I103: Compartida. | J103: Ejecutiva. | L103: a
A104: Jurídico | B104: 2 | C104: Ley Org. 5/2007 Estatuto de Autonomia | D104: 6 | E104: Test competencias 2 | F104: 9 | G104: En enseñanza en toda su extensión, niveles y grados, modalidades y especialidades, tiene la Comunidad Autónoma de Aragón; | H104: Competencia exclusiva. | I104: Competencia compartida. | J104: Competencia ejecutiva. | L104: b
A105: Jurídico | B105: 2 | C105: Ley Org. 5/2007 Estatuto de Autonomia | D105: 6 | E105: Test competencias 2 | F105: 10 | G105: ¿Qué titulo de los siguientes, del Estatuto de Autonomía de Aragón, no está subdividido en cuatro capítulos?: | H105: Economía y Hacienda. | I105: Cooperación Institucional y Acción Exterior. | J105: Competencias de la Comunidad Autónoma. | L105: c
A106: Jurídico | B106: 2 | C106: Ley Org. 5/2007 Estatuto de Autonomia | D106: 6 | E106: Test competencias 2 | F106: 11 | G106: El control de la actividad de los órganos de las Comunidades Autónomas se ejercerá por (señala la NO CORRECTA): | H106: Por el Tribunal de Cuentas, el económico y presupuestario. | I106: Por el Gobierno, previo dictamen del Consejo de Estado, el del ejercicio defunciones delegadas a que se refiere el apartado 2 del artículo 150. | J106: Por el Consejo General del Poder Judicial, el de la administración y sus normas reglamentarias. | L106: c
A107: Jurídico | B107: 2 | C107: Ley Org. 5/2007 Estatuto de Autonomia | D107: 6 | E107: Test competencias 2 | F107: 12 | G107: Conforme a lo establecido en la Constitución Española, la apreciación de la necesidad de armonizar las normas dictadas por las Comunidades Autónomas mediante una ley de las Cortes Generales, corresponde: | H107: Al Tribunal Constitucional. | I107: Al Congreso de los Diputados, por mayoría absoluta. | J107: Al Congreso y al Senado, por mayoría absoluta de cada Cámara. | L107: c
A108: Jurídico | B108: 2 | C108: Ley Org. 5/2007 Estatuto de Autonomia | D108: 6 | E108: Test competencias 2 | F108: 13 | G108: La organización territorial propia de la Comunidad Autónoma de Aragón, es competencia: | H108: Del Estado, conforme a lo establecido en la Constitución Española. | I108: Exclusiva de la CCAA de Aragón, conforme se establece en su Estatuto. | J108: Compartida, la CCAA de Aragón ejercerá el desarrollo legislativo y la ejecución de la legislación básica que establezca el Estado. | L108: b
A109: Jurídico | B109: 2 | C109: Ley Org. 5/2007 Estatuto de Autonomia | D109: 6 | E109: Test competencias 2 | F109: 14 | G109: En el Estatuto de Autonomía de Aragón se establece: | H109: Corresponde a la CCAA de Aragón la competencia compartida en enseñanza en toda su extensión. | I109: La CCAA de Aragón podrá regular, crear y mantener su propia televisión, radio y prensa y, en general, cualquier medio de comunicación social para el cumplimiento de sus fines, respetando la autonomía local. | J109: A y B son correctas. | L109: c
A110: Jurídico | B110: 2 | C110: Ley Org. 5/2007 Estatuto de Autonomia | D110: 6 | E110: Test competencias 2 | F110: 15 | G110: Cuando la CCAA de Aragón ejerce el desarrollo legislativo y la ejecución de la legislación básica que establezca el Estado, nos estamos refiriendo a competencias: | H110: Compartidas. | I110: Ejecutivas. | J110: Exclusivas. | L110: a
A111: Jurídico | B111: 2 | C111: Ley Org. 5/2007 Estatuto de Autonomia | D111: 6 | E111: Test competencias 2 | F111: 16 | G111: La promoción del turismo, conforme se establece en la Constitución Española, se trata de una competencia: | H111: Que puede ser asumida por las Comunidades Autónomas. | I111: Exclusiva del Estado, dado que se trata de una actividad económica importante. | J111: La Constitución no habla del turismo entre los listados de competencias. | L111: a
A112: Jurídico | B112: 2 | C112: Ley Org. 5/2007 Estatuto de Autonomia | D112: 6 | E112: Test competencias 2 | F112: 17 | G112: Es competencia exclusiva de Aragón: | H112: El desarrollo de las bases del Estado para las Administraciones Públicas aragonesas. | I112: Régimen estatutario de los funcionarios de la Comunidad Autónoma. | J112: A y B no son exclusivas de Aragón. | L112: c
A113: Jurídico | B113: 2 | C113: Ley Org. 5/2007 Estatuto de Autonomia | D113: 6 | E113: Test competencias 2 | F113: 18 | G113: En el EAA la gestión de la asistencia sanitaria de la Seguridad Social, se regula como competencia: | H113: Exclusiva. | I113: Compartida. | J113: Ejecutiva. | L113: c
... A121: Jurídico | B121: 3 | C121: Ley 39/2015 Procedimiento Adm. Común. | D121: 7 | E121: Test nº1 alumno | F121: 6 | G121: Según establece el artículo 6.1 de la Ley 39/2015 del procedimiento administrativo común, en el registro electrónico general de apoderamientos del que han de disponer las entidades locales, deberán inscribirse: | H121: Los de carácter general otorgados apud acta, electrónicamente, por quien ostente la condición de interesado en un procedimiento administrativo a favor de representante, para actuar en su nombre ante las Administraciones Públicas, en el que deberá constar el bastanteo realizado del poder. | I121: Los de carácter general otorgados apud acta, presencial o electrónicamente, por quien ostente la condición de interesado en un procedimiento administrativo a favor de representante, para actuar en su nombre ante las Administraciones Públicas, y en el que también deberá constar el bastanteo realizado del poder. | J121: Los de carácter general otorgados apud acta, presencialmente, por quien ostente la condición de interesado en un procedimiento administrativo a favor de representante, para actuar en su nombre ante las Administraciones Públicas, y en el que también deberá constar el bastanteo realizado del poder | L121: b
A122: Jurídico | B122: 3 | C122: Ley 39/2015 Procedimiento Adm. Común. | D122: 7 | E122: Test nº1 alumno | F122: 7 | G122: La Ley 39/2015 del procedimiento administrativo común tiene por objeto: | H122: Regular los requisitos de validez y eficacia de los actos administrativos y el procedimiento administrativo común.. | I122: Regular los principios a los que se debe de ajustarse la iniciativa legislativa y la potestad reglamentaria. | J122: A y B son objeto de la expresada ley | K122: Ninguna es correcta. | L122: c
A123: Jurídico | B123: 3 | C123: Ley 39/2015 Procedimiento Adm. Común. | D123: 7 | E123: Test nº1 alumno | F123: 8 | G123: La Ley 39/2015 de 1 de Octubre, es aplicable: | H123: A la Administración del Estado, de las Comunidades Autónomas y de los Entes Locales, pero no a las entidades instrumentales dependientes de cualquiera de éstas. | I123: A la Administración del Estado, de las Comunidades Autónomas y de los Entes Locales, así como al sector público institucional. | J123: Únicamente a la Administración del Estado. | K123: A la Administración del Estado y, supletoriamente, a la Administración de las Comunidades Autónomas y de los Entes Locales. | L123: b
A124: Jurídico | B124: 3 | C124: Ley 39/2015 Procedimiento Adm. Común. | D124: 7 | E124: Test nº1 alumno | F124: 9 | G124: Están incluidos en el sector público institucional, conforme a la Ley 39/2015 de 1 de Octubre: | H124: Los organismos públicos y entidades de derecho público vinculados o dependientes de las Administraciones Públicas. | I124: Las entidades de derecho privado, vinculados o dependientes de las Administraciones Públicas. | J124: Las Universidades Públicas. | K124: Todas ellas a, b, c integran el sector público institucional a efectos de la Ley 39/2015 de 1 de Octubre del Procedimiento Administrativo común de las Administraciones Públicas. | L124: d
A125: Jurídico | B125: 3 | C125: Ley 39/2015 Procedimiento Adm. Común. | D125: 7 | E125: Test nº1 alumno | F125: 10 | G125: El poder organizativo de la Administración Pública: | H125: Existe en el marco de los registros administrativos. | I125: Es el conjunto de facultades que tiene dicha Administración para determinar su propia estructura y composición, siempre de acuerdo con lo establecido en la Constitución Española y en las leyes. Es la autoorganización. | J125: Se aplica sólo en el marco de los recursos administrativos. | K125: Se aplica en el marco de la contratación del sector público. | L125: b
A126: Jurídico | B126: 3 | C126: Ley 39/2015 Procedimiento Adm. Común. | D126: 7 | E126: Test nº1 alumno | F126: 11 | G126: La ley 39/2015 , de 1 de octubre, del Procedimiento Administrativo Común de las Administraciones Públicas, tiene un total de: | H126: 133 capítulos. | I126: Siete títulos. | J126: A y B son correctas. | K126: Ninguna es correcta. | L126: b
A127: Jurídico | B127: 3 | C127: Ley 39/2015 Procedimiento Adm. Común. | D127: 7 | E127: Test nº1 alumno | F127: 12 | G127: El silencio administrativo: | H127: Es, indistintamente, positivo y negativo, sin que en la práctica prevalezca uno sobre el otro. | I127: Sólo es positivo en los casos expresamente no previstos. | J127: Sólo es negativo en los casos expresamente no previstos. | K127: Es una figura jurídica que actúa como garantía de los administrados. | L127: d
A128: Jurídico | B128: 3 | C128: Ley 39/2015 Procedimiento Adm. Común. | D128: 7 | E128: Test nº1 alumno | F128: 13 | G128: ¿Qué se quiere indicar cuando se dice que el silencio administrativo es positivo? | H128: Que el administrado puede plantear ante los Tribunales de Justicia la cuestión no resuelta por la Administración. | I128: Que si la Administración no contesta a determinada solicitud, se entiende aceptada. | J128: Que ha de seguirse, salvo orden expresa, el criterio de la anterior resolución a una cuestión similar. | K128: Que si la Administración no contesta a determinada solicitud, cabe interponer recurso administrativo. | L128: b
A129: Jurídico | B129: 3 | C129: Ley 39/2015 Procedimiento Adm. Común. | D129: 8 | E129: Test nº2 alumno | F129: 1 | G129: La Ley 39/2015 de 1 de Octubre, tiene por objeto: | H129: Regular los requisitos de validez y eficacia de los actos administrativos y el procedimiento administrativo común. | I129: Regular los principios a los que se debe de ajustarse la iniciativa reglamentaria. | J129: A y B son objeto de la expresada ley | L129: a
A130: Jurídico | B130: 3 | C130: Ley 39/2015 Procedimiento Adm. Común. | D130: 8 | E130: Test nº2 alumno | F130: 2 | G130: Están incluidos en el sector público institucional, conforme a la Ley 39/2015 de 1 de Octubre: | H130: Los organismos públicos y entidades de derecho público vinculados o dependientes de las Administraciones Públicas. | I130: Las entidades de derecho privado, no vinculados o independientes de las Administraciones Públicas. | J130: Todas ellas a, b, integran el sector público institucional a efectos de la Ley 39/2015 de 1 de Octubre del Procedimiento Administrativo común de las Administraciones Públicas. | L130: a
A131: Jurídico | B131: 3 | C131: Ley 39/2015 Procedimiento Adm. Común. | D131: 8 | E131: Test nº2 alumno | F131: 3 | G131: La ley 39/2015 , de 1 de octubre, del Procedimiento Administrativo Común de las Administraciones Públicas, hace referencia a la actividad de las Administraciones Públicas: | H131: En el título I, capítulo I. | I131: En el Título preliminar. | J131: En el título II. | L131: c
A132: Jurídico | B132: 3 | C132: Ley 39/2015 Procedimiento Adm. Común. | D132: 8 | E132: Test nº2 alumno | F132: 4 | G132: La ley 39/2015 , de 1 de octubre, del Procedimiento Administrativo Común de las Administraciones Públicas, hace referencia a “de los interesados en el procedimiento”: | H132: Título III | I132: Título I | J132: Título preliminar | L132: b
A133: Jurídico | B133: 3 | C133: Ley 39/2015 Procedimiento Adm. Común. | D133: 8 | E133: Test nº2 alumno | F133: 5 | G133: Según el artículo 16.6 LPAC podrán hacerse efectivos mediante transferencia dirigida a la oficina pública correspondiente: | H133: Cualesquiera cantidades que haya que satisfacer en el momento de la presentación de documentos a las Administraciones Públicas, sin perjuicio de la posibilidad de su abono por otros medios. | I133: Cualesquiera cantidades que, en concepto tributario, haya que satisfacer en el momento de la presentación de documentos a las Administraciones Públicas, sin perjuicio de la posibilidad de su abono por otros medios | J133: Cualesquiera cantidades que, en concepto tributario, haya que satisfacer con posterioridad a la presentación de documentos a las Administraciones Públicas, sin perjuicio de la posibilidad de su abono por otros medios | L133: a
A134: Jurídico | B134: 3 | C134: Ley 39/2015 Procedimiento Adm. Común. | D134: 8 | E134: Test nº2 alumno | F134: 6 | G134: Conforme a lo establecido en la Ley 39/2015 de 1 de Octubre del procedimiento administrativo común de las Administraciones Públicas, los procedimientos de naturaleza sancionadora: | H134: Se iniciarán siempre de oficio por acuerdo del órgano competente. | I134: Pueden iniciarse de oficio o a solicitud del interesado. | J134: Se iniciarán conforme se establezca en el procedimiento sancionador establecido en la Ley. | K134: Se inician por medio de denuncia. | L134: a
A135: Jurídico | B135: 3 | C135: Ley 39/2015 Procedimiento Adm. Común. | D135: 8 | E135: Test nº2 alumno | F135: 7 | G135: Según el artículo 6.6 de LPAC los poderes inscritos en el registro electrónico de apoderamientos tendrán una validez determinada: | H135: Mínima de cinco años a contar desde la fecha de inscripción. | I135: Máxima de cinco años a contar desde la fecha de inscripción. | J135: Máxima de cinco años a contar desde que son utilizados | L135: b
A136: Jurídico | B136: 3 | C136: Ley 39/2015 Procedimiento Adm. Común. | D136: 8 | E136: Test nº2 alumno | F136: 8 | G136: Según el artículo 9.2 de LPAC los interesados podrán identificarse electrónicamente ante las Administraciones Públicas: | H136: Exclusivamente a través del DNI electrónico. | I136: Exclusivamente a través del DNI electrónico o documento identificativo equivalente. | J136: A través de cualquier sistema que cuente con un registro previo como usuario que permita garantizar su identidad. | L136: c
A137: Jurídico | B137: 3 | C137: Ley 39/2015 Procedimiento Adm. Común. | D137: 8 | E137: Test nº2 alumno | F137: 9 | G137: Según el artículo 11.2 de LPAC las Administraciones Públicas sólo requerirán a los interesados el uso obligatorio de firma para: | H137: Formular solicitudes o presentar declaraciones responsables y renunciar a derechos. | I137: Formular solicitudes, presentar declaraciones responsables o comunicaciones, interponer recursos, desistir de acciones y renunciar a derechos. | J137: Formular solicitudes, presentar declaraciones responsables o comunicaciones, desistir de acciones y renunciar a derechos. | L137: b
A138: Jurídico | B138: 3 | C138: Ley 39/2015 Procedimiento Adm. Común. | D138: 8 | E138: Test nº2 alumno | F138: 10 | G138: De conformidad con lo dispuesto en el artículo 14.1 de LPAC las personas físicas podrán elegir en todo momento si se comunican con las Administraciones Públicas para el ejercicio de sus derechos y obligaciones a través de medios electrónicos o no. | H138: Sí, salvo que estén obligadas a relacionarse a través de medios electrónicos con las Administraciones Públicas. | I138: No, las personas físicas habrán de relacionarse con la Administración en la forma que esta determine. | J138: Ninguna de las respuestas es correcta | L138: a
A139: Jurídico | B139: 3 | C139: Ley 39/2015 Procedimiento Adm. Común. | D139: 8 | E139: Test nº2 alumno | F139: 11 | G139: Según la LPAC (artículo 16.2), concluido el trámite de registro de la respectiva documentación presentada por los interesados: | H139: Los documentos serán cursados sin dilación a sus destinatarios y a las unidades administrativas correspondientes desde el registro en que hubieran sido recibidas. | I139: Los documentos serán en el plazo de 10 días a sus destinatarios y a las unidades administrativas correspondientes desde el registro en que hubieran sido recibidas. | J139: Los documentos serán sin dilación a sus destinatarios o a las unidades administrativas correspondientes desde el registro en que hubieran sido recibidas. | L139: a
A140: Jurídico | B140: 3 | C140: Ley 39/2015 Procedimiento Adm. Común. | D140: 8 | E140: Test nº2 alumno | F140: 12 | G140: Según LPAC (artículo 16.2), en la práctica de los asientos en el registro electrónico la anotación se realizará respetando el orden temporal de: | H140: Recepción o salida de los documentos, e indicarán la fecha del día en que se produzcan. | I140: Recepción o salida de los documentos, e indicarán la fecha del día siguiente al día en que se produzcan. | J140: Recepción de los documentos, e indicarán la fecha del día en que produzcan efectos. | L140: a
A141: Jurídico | B141: 3 | C141: Ley 39/2015 Procedimiento Adm. Común. | D141: 8 | E141: Test nº2 alumno | F141: 13 | G141: De conformidad con lo dispuesto en el artículo 16.4 de la LPAC no es correcto decir que los documentos que los interesados dirijan a los órganos de las Administraciones Públicas pueden presentarse: | H141: En las oficinas de Correos, en la forma que legalmente se establezca. | I141: En las representaciones diplomáticas u oficinas consulares de España en el extranjero. | J141: En las oficinas de asistencia en materia de registros. | L141: a
A142: Jurídico | B142: 3 | C142: Ley 39/2015 Procedimiento Adm. Común. | D142: 8 | E142: Test nº2 alumno | F142: 14 | G142: Según el artículo 16.4 de LPAC los registros electrónicos de todas y cada una de las Administraciones, deberán: | H142: Ser plenamente interoperables, salvo en aquellos casos en los que no se pueda, de modo que se garantice su compatibilidad informática e interconexión, así como la transmisión telemática de los asientos registrales y de los documentos que se presenten en cualquiera de los registros. | I142: Ser plenamente interoperables, de modo que se garantice su compatibilidad informática e interconexión, así como la transmisión telemática de los asientos registrales y de los documentos que se presenten en cualquiera de los registros. | J142: Ser plenamente interoperables, salvo en aquellos casos en los que no se pueda de modo que se garantice su compatibilidad informática e interconexión, sin perjuicio de las fórmulas para la transmisión telemática de los asientos registrales y de los documentos que se presenten en cualquiera de los registros. | L142: b
A143: Jurídico | B143: 3 | C143: Ley 39/2015 Procedimiento Adm. Común. | D143: 8 | E143: Test nº2 alumno | F143: 15 | G143: Según la LPAG (artículo 16.5), cuando los ciudadanos presenten documentos de manera presencial ante las Administraciones públicas: | H143: Sólo se permitirá la presentación de documentos originales, salvo que una norma permita, excepcionalmente, su devolución a los interesados tras su digitalización. | I143: Deberán ser digitalizados, por la oficina de asistencia en materia de registros en la que hayan sido presentados para su incorporación al expediente administrativo electrónico, devolviéndose siempre los originales de los documentos o los objetos aportados al interesado. | J143: Deberán ser digitalizados, por la oficina de asistencia en materia de registros en la que hayan sido presentados, devolviéndose los originales al interesado, sin perjuicio de aquellos supuestos en que la norma determine la custodia por la Administración de los documentos presentados o resulte obligatoria la presentación de objetos o de documentos en un soporte específico no susceptibles de digitalización. | L143: c
A144: Jurídico | B144: 3 | C144: Ley 39/2015 Procedimiento Adm. Común. | D144: 9 | E144: Test nº3 alumno | F144: 2 | G144: De conformidad con lo dispuesto en el artículo 18.2 de LPAC los interesados en un procedimiento que conozcan datos que permitan identificar a otros interesados que no hayan comparecido en él: | H144: Tienen el derecho de proporcionárselos a la Administración actuante. | I144: Tienen el deber de proporcionárselos a la Administración actuante. | J144: Ni tienen el derecho ni tienen el deber de proporcionárselos a la Administración actuante. | L144: b
A145: Jurídico | B145: 3 | C145: Ley 39/2015 Procedimiento Adm. Común. | D145: 9 | E145: Test nº3 alumno | F145: 3 | G145: El artículo 19.1 de LPAC respecto de la comparecencia de las personas ante las oficinas públicas, ya sea presencialmente o por medios electrónicos, dispone que: | H145: Nunca será obligatoria. | I145: Sólo será obligatoria cuando así esté previsto en una norma con rango reglamentario. | J145: Sólo será obligatoria cuando así esté previsto en una norma con rango de ley. | L145: c
A146: Jurídico | B146: 3 | C146: Ley 39/2015 Procedimiento Adm. Común. | D146: 9 | E146: Test nº3 alumno | F146: 4 | G146: Según el artículo 21 de LPAC la Administración está obligada a dictar resolución expresa y a notificarla en todos los procedimientos cualquiera que sea su forma de iniciación (21.1). El plazo máximo en el que debe notificarse la resolución expresa será el fijado por la norma reguladora del correspondiente procedimiento (21.2). Cuando las normas reguladoras de los procedimientos no fijen el plazo máximo, éste será de (21.3): | H146: Seis meses. | I146: Tres meses. | J146: Cuatro meses. | L146: b
... A200: Jurídico | B200: 3 | C200: Ley 39/2015 Procedimiento Adm. Común. | D200: 11 | E200: Test nº5 alumno | F200: 28 | G200: De conformidad con lo establecido en el artículo 95 LPAC, en relación con la caducidad del procedimiento , en los procedimientos iniciados a solicitud del interesado, cuando se produzca su paralización por causa imputable al mismo, la Administración le advertirá que: | H200: Transcurridos tres meses se producirá la caducidad del mismo. | I200: Transcurrido un mes se producirá la caducidad del mismo. | J200: No podrá acordarse la caducidad del procedimiento en los procedimientos iniciados a solicitud del interesado . | L200: a
A201: Jurídico | B201: 4 | C201: R.D.L. 2/2004 Ley Haciendas Locales | D201: 12 | E201: Test Gallocanta 2 | F201: 1 | G201: ¿Qué tributos son exigidos sin contraprestación cuyo hecho imponible está constituido por un negocio que pone de manifiesto la capacidad contributiva del sujeto pasivo como consecuencia de la posesión de un patrimonio? | H201: Las contribuciones especiales. | I201: Los impuestos. | J201: Las tasas. | K201: Los precios públicos. | L201: b
A202: Jurídico | B202: 4 | C202: R.D.L. 2/2004 Ley Haciendas Locales | D202: 12 | E202: Test Gallocanta 2 | F202: 2 | G202: ¿Cómo se denomina el tributo cuyo hecho imponible está constituido por el beneficio de un aumento de valor de los bienes de un sujeto pasivo a raíz de una actuación pública? | H202: Tasa. | I202: Contribución especial. | J202: Impuesto. | K202: Precio público. | L202: b
A203: Jurídico | B203: 4 | C203: R.D.L. 2/2004 Ley Haciendas Locales | D203: 12 | E203: Test Gallocanta 2 | F203: 3 | G203: ¿Qué tipo de tributo es el Impuesto sobre el incremento de valor de los terrenos de naturaleza urbana? | H203: Real. | I203: Directo. | J203: Natural. | K203: Inmediato. | L203: b
A204: Jurídico | B204: 4 | C204: R.D.L. 2/2004 Ley Haciendas Locales | D204: 12 | E204: Test Gallocanta 2 | F204: 4 | G204: ¿Cuál de los siguientes vecinos estará exento de realizar prestaciones personales? | H204: Una persona de 45 años. | I204: Una persona de 50 años. | J204: Una persona de 56 años. | K204: Una persona de 54 años. | L204: c
A205: Jurídico | B205: 4 | C205: R.D.L. 2/2004 Ley Haciendas Locales | D205: 12 | E205: Test Gallocanta 2 | F205: 5 | G205: ¿Cuál de los siguientes no es un tributo? | H205: Las tasas. | I205: Los impuestos. | J205: Los precios públicos. | K205: Las contribuciones especiales. | L205: c
A206: Jurídico | B206: 4 | C206: R.D.L. 2/2004 Ley Haciendas Locales | D206: 12 | E206: Test Gallocanta 2 | F206: 6 | G206: ¿Cuál de los siguientes territorios cuenta con un régimen fiscal especial en la participación en los tributos estatales? | H206: Madrid. | I206: Barcelona. | J206: Ceuta. | K206: Navarra. | L206: d
A207: Jurídico | B207: 4 | C207: R.D.L. 2/2004 Ley Haciendas Locales | D207: 12 | E207: Test Gallocanta 2 | F207: 7 | G207: ¿Qué día se devenga el IBI? | H207: El último día del periodo impositivo. | I207: El primer día del periodo impositivo. | J207: El décimo día hábil del periodo impositivo. | K207: El tercer día hábil del periodo impositivo. | L207: b
A208: Jurídico | B208: 4 | C208: R.D.L. 2/2004 Ley Haciendas Locales | D208: 12 | E208: Test Gallocanta 2 | F208: 8 | G208: ¿A quién le corresponde la facultad originaria para establecer tributos? | H208: Al Estado. | I208: Al Estado y a las Comunidades Autónomas. | J208: Al Estado y a los entes territoriales. | K208: A los entes territoriales. | L208: a
A209: Jurídico | B209: 4 | C209: R.D.L. 2/2004 Ley Haciendas Locales | D209: 12 | E209: Test Gallocanta 2 | F209: 9 | G209: ¿Cuál es el tiempo máximo de prestación personal al año que pueden imponer los ayuntamientos a los residentes en el municipio? | H209: Diez días. | I209: Ocho días. | J209: Quince días. | K209: Veinte días. | L209: c
A210: Jurídico | B210: 4 | C210: R.D.L. 2/2004 Ley Haciendas Locales | D210: 12 | E210: Test Gallocanta 2 | F210: 10 | G210: ¿Qué clase de tributo es el Impuesto que grava las instalaciones, construcciones y obras en un término municipal? | H210: Real. | I210: Social. | J210: Natural. | K210: Indirecto. | L210: d
A211: Jurídico | B211: 4 | C211: R.D.L. 2/2004 Ley Haciendas Locales | D211: 12 | E211: Test Gallocanta 2 | F211: 11 | G211: ¿Qué tipo de potestad tributaria tienen las corporaciones locales? | H211: Primaria. | I211: Originaria. | J211: Derivada. | K211: Común. | L211: c
A212: Jurídico | B212: 4 | C212: R.D.L. 2/2004 Ley Haciendas Locales | D212: 12 | E212: Test Gallocanta 2 | F212: 12 | G212: ¿Cuál de las siguientes normas aprueba el Texto refundido de la Ley de Haciendas Locales? | H212: Real Decreto Legislativo 2/2004, de 5 de marzo | I212: Real Decreto Legislativo 3/2004, de 7 de marzo | J212: Real Decreto Legislativo 5/2004, de 12 de marzo | K212: Real Decreto Legislativo 1/2004, de 15 de marzo | L212: a
... A251: Jurídico | B251: 4 | C251: R.D.L. 2/2004 Ley Haciendas Locales | D251: 13 | E251: Test Alumnos B | F251: 19 | G251: ¿A cuál de las siguientes administraciones es necesario remitir copia del presupuesto de la entidad local? | H251: A la Administración general del Estado | I251: A la Diputación provincial | J251: A la Administración institucional de la Corporación | K251: A la Unión Europea | L251: a
A252: Jurídico | B252: 4 | C252: R.D.L. 2/2004 Ley Haciendas Locales | D252: 13 | E252: Test Alumnos C | F252: 1 | G252: La Ley Reguladora de las Bases del Régimen Local es una ley: | H252: Orgánica. | I252: Ordinaria de carácter básico. | J252: Fundamental. | L252: b
A253: Jurídico | B253: 4 | C253: R.D.L. 2/2004 Ley Haciendas Locales | D253: 13 | E253: Test Alumnos C | F253: 2 | G253: El gasto de los recursos con que cuentan las entidades Locales debe efectuarse de acuerdo con las previsiones contenidas en sus: | H253: Presupuestos. | I253: Ordenanzas. | J253: Servicios. | L253: a
A254: Jurídico | B254: 4 | C254: R.D.L. 2/2004 Ley Haciendas Locales | D254: 13 | E254: Test Alumnos C | F254: 3 | G254: El Presupuesto de la Corporación se considera definitivamente aprobado: | H254: Cuando en el plazo previsto para la información pública no se hayan presentado reclamaciones. | I254: En el plazo de dos meses desde su exposición al público. | J254: Cuando haya transcurrido un mes desde su publicación en el Diario Oficial correspondiente. | L254: a
A255: Jurídico | B255: 4 | C255: R.D.L. 2/2004 Ley Haciendas Locales | D255: 13 | E255: Test Alumnos C | F255: 4 | G255: ¿Cuál es la última fase del proceso de ejecución del gasto presupuestario? | H255: La disposición de gasto | I255: La ordenación del pago | J255: El reconocimiento de la obligación | K255: La autorización del gasto | L255: b
A256: Jurídico | B256: 4 | C256: R.D.L. 2/2004 Ley Haciendas Locales | D256: 13 | E256: Test Alumnos C | F256: 5 | G256: ¿Cuál es la primera fase del proceso de ejecución del gasto presupuestario? | H256: El reconocimiento de la obligación | I256: La autorización del gasto | J256: La ordenación del pago | K256: La disposición de gasto | L256: b
A257: Jurídico | B257: 4 | C257: R.D.L. 2/2004 Ley Haciendas Locales | D257: 13 | E257: Test Alumnos C | F257: 8 | G257: En los Ayuntamientos, con carácter general, las funciones de ordenación de pagos: | H257: Competen al Alcalde. | I257: Las realiza el órgano que determine el Pleno. | J257: Las realiza en todo caso la unidad de ordenación de pagos. | K257: Ninguna es correcta. | L257: a
A258: Jurídico | B258: 4 | C258: R.D.L. 2/2004 Ley Haciendas Locales | D258: 13 | E258: Test Alumnos C | F258: 15 | G258: Se considera vehículo apto para la circulación, a efectos del Impuesto sobre Vehículos de Tracción Mecánica: | H258: El que hubiera sido matriculado en los registros públicos correspondientes y mientras no haya causado baja en éstos. | I258: Entre otros, a los efectos de este impuesto se considerarán aptos los vehículos provistos de permisos temporales y matrícula turística. | J258: A y B son correctas. | K258: A y b no son correctas. | L258: c
A259: Jurídico | B259: 4 | C259: R.D.L. 2/2004 Ley Haciendas Locales | D259: 13 | E259: Test Alumnos C | F259: 16 | G259: Según el artículo 92 del texto refundido de la Ley Reguladora de las Haciendas Locales, aprobado por Real Decreto Legislativo 2/2004, de 5 de marzo, no están sujetos al Impuesto sobre Vehículos de Tracción Mecánica: | H259: Los remolques y semirremolques arrastrados por vehículos de tracción mecánica cuya carga útil sea superior a 800 kilogramos. | I259: Los vehículos que habiendo sido dados de baja en los Registros por antigüedad de su modelo, puedan ser autorizados para circular excepcionalmente con ocasión de exhibiciones, certámenes o carreras limitadas a los de esta naturaleza. | J259: Los remolques y semirremolques arrastrados por vehículos de tracción mecánica cuya carga útil no sea superior a 950 kilogramos. | K259: Los remolques y semirremolques arrastrados por vehículos de tracción mecánica cuya carga útil sea superior a 850 kilogramos. | L259: b
A260: Jurídico | B260: 4 | C260: R.D.L. 2/2004 Ley Haciendas Locales | D260: 13 | E260: Test Alumnos C | F260: 17 | G260: Según el artículo 72 del texto refundido de la Ley Reguladora de las Haciendas Locales, aprobado por Real Decreto Legislativo 2/2004, de 5 de marzo, a efectos del Impuesto sobre Bienes Inmuebles: | H260: El tipo de gravamen aplicable a los bienes inmuebles de características especiales, que tendrá carácter supletorio, será del 0,6 por ciento. Los ayuntamientos podrán establecer para cada grupo de ellos existentes en el municipio un tipo diferenciado que, en ningún caso, será inferior al 0,3 por ciento ni superior al 1,4 por ciento. | I260: El tipo de gravamen aplicable a los bienes inmuebles de características especiales, que tendrá carácter supletorio, será del 0,5 por ciento. Los ayuntamientos podrán establecer para cada grupo de ellos existentes en el municipio un tipo diferenciado que, en ningún caso, será inferior al 0,3 por ciento ni superior al 1,4 por ciento. | J260: El tipo de gravamen aplicable a los bienes inmuebles de características especiales, que tendrá carácter supletorio, será del 0,6 por ciento. Los ayuntamientos podrán establecer para cada grupo de ellos existentes en el municipio un tipo diferenciado que, en ningún caso, será inferior al 0,4 por ciento ni superior al 1,3 por ciento. | K260: Ninguna es correcta. | L260: c
A261: Jurídico | B261: 4 | C261: R.D.L. 2/2004 Ley Haciendas Locales | D261: 13 | E261: Test Alumnos C | F261: 19 | G261: ¿Cuál de los siguientes conceptos corresponde a uno de los niveles de la clasificación económica del estado de gastos del presupuesto? | H261: Función. | I261: Programa. | J261: Concepto. | K261: Subfunción | L261: c
A262: Jurídico | B262: 4 | C262: R.D.L. 2/2004 Ley Haciendas Locales | D262: 13 | E262: Test Alumnos C | F262: 20 | G262: ¿Cómo se denomina el acto mediante el cual se declara la existencia de un crédito exigible contra la entidad derivado de un gasto autorizado y dispuesto o comprometido? | H262: Reconocimiento y liquidación de la obligación. | I262: Liquidación del pago. | J262: Ordenación del pago. | K262: Autorización del pago. | L262: a
A263: Jurídico | B263: 5 | C263: Ley 7/1985 Reguladora de las Bases del Regimen Local | D263: 14 | E263: Test Administracion 2 | F263: 1 | G263: Con la Ley 57/2003, de 16 de diciembre, de medidas para la modernización del gobierno local, los municipios de gran población asumen nuevas competencias y financiación en materia de: | H263: Se prevén nuevas competencias en participación ciudadana | I263: Se prevén nuevas competencias obligatorias en materia urbanística. | J263: No hay nuevas competencias para los municipios ni mayor financiación, sólo una serie de cambios en cuanto a organización. | K263: No se prevén nuevas competencias obligatorias pero sí mayores recursos financieros para estos municipios. | L263: c
A264: Jurídico | B264: 5 | C264: Ley 7/1985 Reguladora de las Bases del Regimen Local | D264: 14 | E264: Test Administracion 2 | F264: 2 | G264: El Alcalde, en los municipios de gran población, podrá delegar sus funciones cuando le esté permitido en: | H264: La Junta de Gobierno Local, los miembros de la Junta de Gobierno Local que ostenten la condición concejales y en los coordinadores generales únicamente | I264: Los miembros de la Junta de Gobierno Local qué ostenten la condición de concejales, en los coordinadores generales y en los directores generales u órganos similares únicamente | J264: Los miembros de la junta de Gobierno Local, en los coordinadores generales y en los directores generales u órganos similares únicamente | K264: La Junta de Gobierno Local, en sus miembros, en los demás concejales y, en su caso, en los coordinadores generales, directores generales u órganos similares. | L264: d
A265: Jurídico | B265: 5 | C265: Ley 7/1985 Reguladora de las Bases del Regimen Local | D265: 14 | E265: Test Administracion 2 | F265: 3 | G265: En los municipios con régimen de gran población, únicamente pueden delegarse las competencias del Pleno permitidas: | H265: a favor de la Junta de Gobierno Local | I265: a favor del alcalde | J265: a favor de las comisiones | K265: a favor de los órganos directivos | L265: c
A266: Jurídico | B266: 5 | C266: Ley 7/1985 Reguladora de las Bases del Regimen Local | D266: 14 | E266: Test Administracion 2 | F266: 4 | G266: En un municipio de régimen de gran población, una vez redactado el proyecto de una ordenanza, el siguiente paso sería someterla a: | H266: Información pública | I266: Aprobación por el pleno | J266: Dictamen de la comisión informativa competente | K266: Aprobación de la Junta de Gobierno local | L266: d
... A292: Jurídico | B292: 5 | C292: Ley 7/1985 Reguladora de las Bases del Regimen Local | D292: 16 | E292: Test Administracion 3 | F292: 10 | G292: En los municipios en que rige el régimen de Concejo Abierto, podrá otorgarse representación a favor de otro miembro de la Asamblea: | H292: Únicamente para cada sesión. | I292: Para cada sesión o con carácter indefinido durante el periodo entre elecciones locales. | J292: Únicamente con carácter indefinido durante el periodo de elecciones locales. | K292: No se puede. | L292: b
A293: Jurídico | B293: 5 | C293: Ley 7/1985 Reguladora de las Bases del Regimen Local | D293: 16 | E293: Test Administracion 3 | F293: 11 | G293: Conforme a lo establecido en la Constitución Española ¿Quién elige al Alcalde?: | H293: Los Concejales. | I293: Los vecinos. | J293: Los concejales o los vecinos. | L293: c
...

Sheet Conteo
A2: Etiquetas de fila | B2: Cuenta de Pregunta
A3: Específico | B3: 1623
A4: Carpinteria | B4: 252
A5: Albañileria | B5: 210
A6: Ofimatica | B6: 167
A7: Aparatos de audio, video e imagen | B7: 165
A8: Fontaneria | B8: 159
A9: Persianas | B9: 118
A10: Prevencion | B10: 75
A11: Incendios | B11: 73
A12: Electricidad | B12: 59
A13: Cerrajeria | B13: 53
A14: Alarmas | B14: 52
... A35: Prevencion | B35: 3
A36: (en blanco)
A37: (en blanco)
A38: Total general | B38: 2355

Sheet Temas
A1: Temario | B1: Tema | C1: Descripcion_Tema
A2: Específico | B2: 0 | C2: Supuestos Practicos
A3: Jurídico | B3: 1 | C3: Constitución
A4: Jurídico | B4: =B3+1 -> 2 | C4: Ley Org. 5/2007 Estatuto de Autonomia
A5: Jurídico | B5: =B4+1 -> 3 | C5: Ley 39/2015 Procedimiento Adm. Común.
A6: Jurídico | B6: =B5+1 -> 4 | C6: R.D.L. 2/2004 Ley Haciendas Locales
A7: Jurídico | B7: =B6+1 -> 5 | C7: Ley 7/1985 Reguladora de las Bases del Regimen Local
A8: Jurídico | B8: =B7+1 -> 6 | C8: R.D.L. 5/2015 T.R.E.B.E.P
A9: Jurídico | B9: =B8+1 -> 7 | C9: Ley 10/2017 Regimen especial Municipio Zaragoza
A10: Jurídico | B10: =B9+1 -> 8 | C10: Ley 3/2007 Igualdad
A11: Específico | B11: =B10+1 -> 9 | C11: Electricidad
A12: Específico | B12: =B11+1 -> 10 | C12: Albañileria
A13: Específico | B13: =B12+1 -> 11 | C13: Fontaneria
A14: Específico | B14: =B13+1 -> 12 | C14: Carpinteria
A15: Específico | B15: =B14+1 -> 13 | C15: Cerrajeria
... A37: Específico | B37: =B36+1 -> 35 | C37: Productos fitosanitarios

Sheet Estrategia
A1: Preguntas totales | B1: 50 | D1: Estrategia, si me suena alguna respuesta, valorar. Si descarto 1 respuesta, jugarmela
A2: Penalizacion | B2: 0.33
A4: Aciertos | B4: 45 | C4: 40 | D4: 35 | E4: 30 | F4: 25
A5: Fallos | B5: 0 | C5: 0 | D5: 0 | E5: 0 | F5: 0
A6: NOTA | B6: =(B4-(B5*$B$2))/$B$1*10 -> 9 | C6: =(C4-(C5*$B$2))/$B$1*10 -> 8 | D6: =(D4-(D5*$B$2))/$B$1*10 -> 7 | E6: =(E4-(E5*$B$2))/$B$1*10 -> 6 | F6: =(F4-(F5*$B$2))/$B$1*10 -> 5
A8: 5 fallos | B8: =(5*B2)/B1*10 -> 0.33
A9: 10 fallos | B9: =(10*B2)/B1*10 -> 0.66
A10: 15 fallos | B10: =(15*B2)/B1*10 -> 0.99
